rbceq2/__init__.py
rbceq2/main.py
rbceq2/IO/PDF_reports.py
rbceq2/IO/__init__.py
rbceq2/IO/encoders.py
rbceq2/IO/record_data.py
rbceq2/IO/validation.py
rbceq2/IO/vcf.py
rbceq2/core_logic/__init__.py
rbceq2/core_logic/alleles.py
rbceq2/core_logic/co_existing.py
rbceq2/core_logic/constants.py
rbceq2/core_logic/data_procesing.py
rbceq2/core_logic/large_variants.py
rbceq2/core_logic/utils.py
rbceq2/db/__init__.py
rbceq2/db/db.py
rbceq2/filters/__init__.py
rbceq2/filters/geno.py
rbceq2/filters/knops.py
rbceq2/filters/phased.py
rbceq2/filters/shared_filter_functionality.py
rbceq2/phenotype/__init__.py
rbceq2/phenotype/antigens.py
rbceq2/phenotype/choose_pheno.py
rbceq2/resources/db.tsv
rbceq2/resources/db_backup.tsv
rbceq2-2.4.1.dist-info/licenses/LICENSE
rbceq2-2.4.1.dist-info/METADATA
rbceq2-2.4.1.dist-info/WHEEL
rbceq2-2.4.1.dist-info/entry_points.txt
rbceq2-2.4.1.dist-info/top_level.txt
rbceq2-2.4.1.dist-info/RECORD
