Metadata-Version: 2.4
Name: rbceq2
Version: 2.4.1
Summary: Call ISBT alleles from VCF/s
Author-email: Liam McIntyre <limcintyre@redcrossblood.org.au>
License: Copyright 2025 Australian Red Cross Lifeblood
Classifier: Programming Language :: Python :: 3
Classifier: Programming Language :: Python :: 3.12
Classifier: License :: OSI Approved :: MIT License
Classifier: Operating System :: OS Independent
Classifier: Intended Audience :: Science/Research
Classifier: Intended Audience :: Developers
Classifier: Topic :: Scientific/Engineering :: Bio-Informatics
Requires-Python: >=3.12
License-File: LICENSE
Requires-Dist: pandas>=2.2.2
Requires-Dist: polars>=0.20.26
Requires-Dist: icecream>=2.1
Requires-Dist: loguru>=0.7.2
Requires-Dist: pyarrow>=18.1
Requires-Dist: reportlab>=4.3.1
Requires-Dist: frozendict>=2.4.6
Provides-Extra: dev
Requires-Dist: flake8>=3.9.2; extra == "dev"
Requires-Dist: coverage>=7.0; extra == "dev"
Dynamic: license-file
